orbuculum_client/__init__.py
orbuculum_client/api_client.py
orbuculum_client/api_response.py
orbuculum_client/configuration.py
orbuculum_client/exceptions.py
orbuculum_client/py.typed
orbuculum_client/rest.py
orbuculum_client/api/__init__.py
orbuculum_client/api/account_api.py
orbuculum_client/api/account_permissions_api.py
orbuculum_client/api/authentication_api.py
orbuculum_client/api/custom_api.py
orbuculum_client/api/entity_api.py
orbuculum_client/api/entity_permissions_api.py
orbuculum_client/api/label_api.py
orbuculum_client/api/label_permissions_api.py
orbuculum_client/api/limitation_api.py
orbuculum_client/api/transaction_api.py
orbuculum_client/models/__init__.py
orbuculum_client/models/account.py
orbuculum_client/models/account_created_response.py
orbuculum_client/models/account_created_response_data.py
orbuculum_client/models/account_deleted_response.py
orbuculum_client/models/account_deleted_response_data.py
orbuculum_client/models/account_permission.py
orbuculum_client/models/account_updated_response.py
orbuculum_client/models/account_updated_response_data.py
orbuculum_client/models/activate_account_request.py
orbuculum_client/models/activate_entity200_response.py
orbuculum_client/models/activate_entity200_response_data.py
orbuculum_client/models/activate_entity_request.py
orbuculum_client/models/add_commission_request.py
orbuculum_client/models/column_info.py
orbuculum_client/models/commission_created_response.py
orbuculum_client/models/commission_data.py
orbuculum_client/models/create_account_permission_request.py
orbuculum_client/models/create_account_request.py
orbuculum_client/models/create_custom_record_request.py
orbuculum_client/models/create_custom_record_response.py
orbuculum_client/models/create_entity201_response.py
orbuculum_client/models/create_entity201_response_data.py
orbuculum_client/models/create_entity_permission_request.py
orbuculum_client/models/create_entity_request.py
orbuculum_client/models/create_label_permission_request.py
orbuculum_client-0.3.0.dist-info/licenses/LICENSE
orbuculum_client-0.3.0.dist-info/METADATA
orbuculum_client-0.3.0.dist-info/WHEEL
orbuculum_client-0.3.0.dist-info/top_level.txt
orbuculum_client-0.3.0.dist-info/RECORD
