Metadata-Version: 2.4
Name: orbuculum-client
Version: 0.3.0
Summary: Official Python client for the Orbuculum API - accounting and finance automation
Author-email: Orbuculum Team <i@orbuculum.app>
License-Expression: MIT
Project-URL: Homepage, https://github.com/orbuculum-app/orbuculum-python-client
Project-URL: Repository, https://github.com/orbuculum-app/orbuculum-python-client
Project-URL: Issues, https://github.com/orbuculum-app/orbuculum-python-client/issues
Project-URL: Documentation, https://s1.orbuculum.app/swagger
Keywords: orbuculum,api,client,accounting,finance,automation
Classifier: Development Status :: 3 - Alpha
Classifier: Intended Audience :: Developers
Classifier: Operating System :: OS Independent
Classifier: Programming Language :: Python :: 3
Classifier: Programming Language :: Python :: 3.9
Classifier: Programming Language :: Python :: 3.10
Classifier: Programming Language :: Python :: 3.11
Classifier: Programming Language :: Python :: 3.12
Classifier: Programming Language :: Python :: 3.13
Classifier: Topic :: Software Development :: Libraries :: Python Modules
Classifier: Topic :: Office/Business :: Financial :: Accounting
Requires-Python: >=3.9
License-File: LICENSE
Requires-Dist: urllib3<3.0.0,>=2.1.0
Requires-Dist: python-dateutil>=2.8.2
Requires-Dist: pydantic>=2
Requires-Dist: typing-extensions>=4.7.1
Requires-Dist: lazy-imports<2,>=1
Provides-Extra: dev
Requires-Dist: pytest>=7.2.1; extra == "dev"
Requires-Dist: pytest-cov>=2.8.1; extra == "dev"
Requires-Dist: tox>=3.9.0; extra == "dev"
Requires-Dist: flake8>=4.0.0; extra == "dev"
Requires-Dist: types-python-dateutil>=2.8.19.14; extra == "dev"
Requires-Dist: mypy>=1.5; extra == "dev"
Dynamic: license-file
